{
  "usuarios": [
    {
      "id": 1,
      "email": "cliente@elaine.com",
      "senha": "$2b$10$cuUlXpShcTxVLESlEdQLZ.PUXngo7MISwp7SBSHSz/lTFOos7cfWu",
      "isAdmin": true,
      "endereco": "Rua das Flores, 123",
      "telefone": "(11) 99999-1111",
      "cpf": "123.456.789-00",
      "cnpj": null,
      "dataNascimento": "1995-08-10"
    },
    {
      "id": 2,
      "email": "novo@cliente.com",
      "senha": "$2b$10$QSYeK6/qvLYCCpmpGTMEaecLZY1p5aZIQ.deb.cECT9dg0OD9UWJa",
      "isAdmin": false,
      "endereco": "a440a2235a5ad1409b468158b9f2a67e:12880ace37b4258403",
      "telefone": "8540adb6e39626ad9a62c484ba64a6ab:3a2de5fef784e83291ce66",
      "cpf": "9ae27cc895b4950041208359104365cf:c3b9c93ace00a694e2f21a",
      "dataNascimento": "c29d50b627e61dbf5c0b017346f4f9b6:9e30b3abc7ef9a3de926"
    },
    {
      "id": 3,
      "email": "gui@gui.com",
      "senha": "$2b$10$gsUHPLJwZv2FSrJMVLNtnu2tlSSHKG4Fv6fV7crpaJUDcMSF5EKui",
      "isAdmin": false,
      "endereco": "5fe1ae8e8163bf813450f012bf741b4b:a31027fe00",
      "telefone": "d1074540b449cdcb8037c8a1ae01555e:e54812d07c06e6cccafe",
      "cpf": "1ac3fbf761490bb3347dc33111fe8eae:424a60bbd78565e251b4ee",
      "dataNascimento": "e17e6d51bc104a9bff59377ce28480dc:3a029cdf57dc6341c949"
    }
  ],
  "configuracaoEntrega": {
    "tempoMinimoMinutos": 25,
    "tempoMaximoMinutos": 45,
    "mensagemLivre": "Prazo sujeito a variacao conforme demanda.",
    "updatedByUsuarioId": 1,
    "updatedAt": "2026-06-07T13:42:18.208Z"
  },
  "produtos": [
    {
      "id": 1,
      "nome": "Bolo de Chocolate",
      "descricao": "Bolo recheado com brigadeiro",
      "tamanho": "1kg",
      "tipo": "BOLO",
      "precoUnitario": 95,
      "anexo": [
        "/assets/produtos/bolo-chocolate.png"
      ],
      "imagemUrl": "/assets/produtos/bolo-chocolate.png",
      "imagemAlt": "Bolo de chocolate com cobertura de brigadeiro"
    },
    {
      "id": 2,
      "nome": "Bolo Red Velvet",
      "descricao": "Massa aveludada com cream cheese",
      "tamanho": "1kg",
      "tipo": "BOLO",
      "precoUnitario": 110,
      "anexo": [
        "/assets/produtos/bolo-red-velvet.png"
      ],
      "imagemUrl": "/assets/produtos/bolo-red-velvet.png",
      "imagemAlt": "Bolo red velvet com cobertura de cream cheese"
    },
    {
      "id": 3,
      "nome": "Caixa de Cupcakes",
      "descricao": "Caixa com 6 cupcakes decorados",
      "tamanho": "6 unidades",
      "tipo": "CUPCAKE",
      "precoUnitario": 48,
      "anexo": [
        "/assets/produtos/caixa-cupcakes.png"
      ],
      "imagemUrl": "/assets/produtos/caixa-cupcakes.png",
      "imagemAlt": "Caixa com seis cupcakes decorados"
    },
    {
      "id": 4,
      "nome": "Torta de Limão",
      "descricao": "Torta gelada com merengue",
      "tamanho": "8 fatias",
      "tipo": "TORTA",
      "precoUnitario": 72,
      "anexo": [
        "/assets/produtos/torta-limao.png"
      ],
      "imagemUrl": "/assets/produtos/torta-limao.png",
      "imagemAlt": "Torta de limao com merengue tostado"
    }
  ],
  "massas": [
    {
      "id": 1,
      "descricao": "Pão de ló de chocolate"
    },
    {
      "id": 2,
      "descricao": "Massa amanteigada de baunilha"
    },
    {
      "id": 3,
      "descricao": "Red velvet tradicional"
    }
  ],
  "sabores": [
    {
      "id": 1,
      "descricao": "Brigadeiro belga"
    },
    {
      "id": 2,
      "descricao": "Ninho com morango"
    },
    {
      "id": 3,
      "descricao": "Doce de leite"
    },
    {
      "id": 4,
      "descricao": "Limão siciliano"
    }
  ],
  "tabelasPreco": [
    {
      "id": 1,
      "descricao": "Tabela vigente 2026",
      "dataInicio": "2026-01-01T00:00:00.000Z",
      "dataFim": null,
      "atual": true
    },
    {
      "id": 2,
      "descricao": "Tabela promocional 2025",
      "dataInicio": "2025-06-01T00:00:00.000Z",
      "dataFim": "2025-12-31T23:59:59.000Z",
      "atual": false
    }
  ],
  "tpItems": [
    {
      "id": 1,
      "tabelaPrecoId": 1,
      "produtoId": 1,
      "preco": 95
    },
    {
      "id": 2,
      "tabelaPrecoId": 1,
      "produtoId": 2,
      "preco": 110
    },
    {
      "id": 3,
      "tabelaPrecoId": 1,
      "produtoId": 3,
      "preco": 48
    },
    {
      "id": 4,
      "tabelaPrecoId": 1,
      "produtoId": 4,
      "preco": 72
    },
    {
      "id": 5,
      "tabelaPrecoId": 2,
      "produtoId": 1,
      "preco": 88
    },
    {
      "id": 6,
      "tabelaPrecoId": 2,
      "produtoId": 2,
      "preco": 104
    },
    {
      "id": 7,
      "tabelaPrecoId": 2,
      "produtoId": 3,
      "preco": 44
    },
    {
      "id": 8,
      "tabelaPrecoId": 2,
      "produtoId": 4,
      "preco": 68
    }
  ],
  "pedidos": [
    {
      "id": 1,
      "usuarioId": 1,
      "nomeRecebedor": "Elaine Souza",
      "endereco": "Rua das Flores, 123",
      "complemento": "Casa 2",
      "referencia": "Portao branco",
      "tipoEntrega": "ENTREGA",
      "melhorHorarioEntrega": "14:00",
      "observacoes": "Entregar na portaria",
      "anexo": [],
      "valorTotal": 185,
      "desconto": 5,
      "status": "SAIU_PARA_ENTREGA",
      "itens": [
        {
          "id": 1,
          "produtoId": 1,
          "quantidade": 2,
          "preco": 95
        }
      ]
    },
    {
      "id": 2,
      "usuarioId": 1,
      "nomeRecebedor": "",
      "endereco": "",
      "complemento": "",
      "referencia": "",
      "tipoEntrega": "RETIRADA",
      "melhorHorarioEntrega": "",
      "observacoes": "Cliente retira no balcao",
      "anexo": [],
      "valorTotal": 48,
      "desconto": 0,
      "status": "EM_PREPARO",
      "itens": [
        {
          "id": 2,
          "produtoId": 3,
          "quantidade": 1,
          "preco": 48
        }
      ]
    },
    {
      "id": 3,
      "usuarioId": 1,
      "endereco": "Rua Persistida, 77",
      "tipoEntrega": "ENTREGA",
      "anexo": [],
      "valorTotal": 110,
      "desconto": 0,
      "status": "EM_ABERTO",
      "itens": [
        {
          "id": 3,
          "produtoId": 2,
          "quantidade": 1,
          "preco": 110
        }
      ]
    },
    {
      "id": 4,
      "usuarioId": 1,
      "endereco": "Rua Ministro Lindolfo Collor, n° 215, Bairro Primeiro de Maio",
      "tipoEntrega": "ENTREGA",
      "anexo": [],
      "valorTotal": 1100,
      "desconto": 0,
      "status": "EM_ABERTO",
      "itens": [
        {
          "id": 4,
          "produtoId": 2,
          "quantidade": 10,
          "preco": 110
        }
      ]
    },
    {
      "id": 5,
      "usuarioId": 1,
      "endereco": "Rua Ministro Linfoldo Collor, n 215, bairro Primeiro de Maio",
      "tipoEntrega": "ENTREGA",
      "anexo": [],
      "valorTotal": 288,
      "desconto": 12,
      "status": "EM_ABERTO",
      "itens": [
        {
          "id": 5,
          "produtoId": 1,
          "quantidade": 2,
          "preco": 95
        },
        {
          "id": 6,
          "produtoId": 2,
          "quantidade": 1,
          "preco": 110
        }
      ]
    },
    {
      "id": 6,
      "usuarioId": 1,
      "endereco": "sdgasgdrg",
      "tipoEntrega": "ENTREGA",
      "anexo": [],
      "valorTotal": 226,
      "desconto": 12,
      "status": "EM_ABERTO",
      "itens": [
        {
          "id": 7,
          "produtoId": 1,
          "quantidade": 2,
          "preco": 95
        },
        {
          "id": 8,
          "produtoId": 3,
          "quantidade": 1,
          "preco": 48
        }
      ]
    }
  ],
  "counters": {
    "usuario": 4,
    "pedido": 7,
    "pedidoItem": 9,
    "produto": 5,
    "massa": 4,
    "sabor": 5,
    "tabelaPreco": 3,
    "tpItem": 9
  }
}